<PAMDataset>
  <PAMRasterBand band="1">
    <Description>kd1</Description>
    <Histograms>
      <HistItem>
        <HistMin>0</HistMin>
        <HistMax>231.4770812988281</HistMax>
        <BucketCount>256</BucketCount>
        <IncludeOutOfRange>1</IncludeOutOfRange>
        <Approximate>0</Approximate>
        <HistCounts>24827|2789|2207|1654|1267|1139|998|926|863|881|846|792|729|834|746|725|703|666|692|654|648|600|641|574|561|551|566|556|551|536|522|486|480|484|422|440|410|420|445|421|416|422|418|370|384|360|344|373|332|330|299|277|246|259|242|232|209|243|240|203|251|229|244|244|232|258|215|213|206|195|197|182|182|177|166|178|152|155|143|138|107|109|114|95|105|96|96|93|98|97|81|77|78|57|74|75|57|68|71|57|41|59|46|45|48|47|45|42|41|42|49|44|44|40|34|44|45|38|43|35|36|42|42|40|36|36|31|38|39|35|28|26|22|20|19|19|17|23|17|19|20|25|16|22|19|19|17|15|10|12|10|16|12|10|12|13|12|10|11|9|12|10|11|11|12|15|10|5|14|11|13|9|13|12|8|6|8|16|7|12|13|8|13|13|12|4|10|12|9|9|11|9|11|11|13|9|6|11|10|11|9|9|12|7|10|8|13|9|9|11|12|7|7|11|6|13|10|12|6|10|8|9|10|10|7|9|11|8|10|12|5|11|7|8|10|9|12|8|8|7|8|12|7|11|8|6|8|14|9|6|8|10|8|9|3|1</HistCounts>
      </HistItem>
    </Histograms>
  </PAMRasterBand>
</PAMDataset>
